{"api_auth_index.md":"fc3652cf","api_examples_index.md":"beba606d","api_examples_product-with-variants_index.md":"b9a6ed08","api_index.md":"fffc2c5a","api_products_index.md":"f1cb6af5","api_products_product-brands.md":"72c02cc6","api_products_product-category.md":"6e1c9fc1","api_products_product-definition.md":"4ae96d0e","api_products_product-images.md":"533e3709","api_products_product-instances-group.md":"2955d462","api_products_product-instances.md":"c3d4b332","api_products_product-listing.md":"641fe251","api_products_product-options.md":"f1e2e044","api_products_product-properties.md":"72826d77","api_products_product-search.md":"7600d0a6","api_products_product-types.md":"871acdb8","api_products_product-variants.md":"88c492a9","api_products_product.md":"3313b260","api_shopping-cart_index.md":"85c90e9e","architecture_index.md":"f2b0066a","build-and-run.md":"6e187acc","configuration_database.md":"4cbf6d12","configuration_emails.md":"10a426f9","docker.md":"d3c8bbaa","index.md":"faf99bc2","model_country-zones.md":"bf4d3056","model_merchant.md":"60e71667","model_product-references.md":"7710bc46","model_user.md":"1ed0a0d8","operations_reset-password.md":"b323e00a","tools_translation.md":"23c60337","what-is-shopizer.md":"488899eb"}
